LICENSE
README.rst
setup.cfg
setup.py
src/reliapy/__init__.py
src/reliapy/_messages.py
src/reliapy/math.py
src/reliapy.egg-info/PKG-INFO
src/reliapy.egg-info/SOURCES.txt
src/reliapy.egg-info/dependency_links.txt
src/reliapy.egg-info/requires.txt
src/reliapy.egg-info/top_level.txt
src/reliapy/distributions/__init__.py
src/reliapy/distributions/joint_distribution.py
src/reliapy/distributions/continuous/__init__.py
src/reliapy/distributions/continuous/_continuous.py
src/reliapy/distributions/continuous/_normal.py
src/reliapy/monte_carlo/__init__.py
src/reliapy/monte_carlo/_monte_carlo.py
src/reliapy/monte_carlo/_simulation.py
src/reliapy/state_limit/__init__.py
src/reliapy/state_limit/_model.py
src/reliapy/transformation/__init__.py
src/reliapy/transformation/_form.py
src/reliapy/transformation/_fosm.py
src/reliapy/transformation/_optimization.py